pybakul/__init__.py
pybakul/tools.py
pybakul-0.1.0.dist-info/METADATA
pybakul-0.1.0.dist-info/WHEEL
pybakul-0.1.0.dist-info/top_level.txt
pybakul-0.1.0.dist-info/RECORD
