Metadata-Version: 2.4
Name: pybakul
Version: 0.1.0
Summary: String utility package with character frequency and string reversal
Author-email: Bakul Sarkar <your.email@example.com>
License: MIT
Project-URL: Homepage, https://github.com/yourusername/pybakul
Requires-Python: >=3.7
